eth_client_utils/__init__.py
eth_client_utils/client.py
eth_client_utils/utils.py
ethereum_client_utils-0.3.2.dist-info/DESCRIPTION.rst
ethereum_client_utils-0.3.2.dist-info/METADATA
ethereum_client_utils-0.3.2.dist-info/metadata.json
ethereum_client_utils-0.3.2.dist-info/RECORD
ethereum_client_utils-0.3.2.dist-info/top_level.txt
ethereum_client_utils-0.3.2.dist-info/WHEEL
